discord_logging/__init__.py
discord_logging/examples.py
discord_logging/handler.py
python_logging_discord_handler-0.1.4.dist-info/LICENSE.txt
python_logging_discord_handler-0.1.4.dist-info/WHEEL
python_logging_discord_handler-0.1.4.dist-info/METADATA
python_logging_discord_handler-0.1.4.dist-info/RECORD
